metatrader/__init__.py
metatrader/client.py
metatrader/logging.py
metatrader/socketio.py
metatrader/models/__init__.py
metatrader/models/account_models.py
metatrader/models/enum_types.py
metatrader/models/events.py
metatrader/models/exchange_info_models.py
metatrader/models/kline_models.py
metatrader/models/mt_models.py
metatrader/models/orders_models.py
metatrader/models/symbol_models.py
metatrader_sockets_client-0.0.4.dist-info/METADATA
metatrader_sockets_client-0.0.4.dist-info/WHEEL
metatrader_sockets_client-0.0.4.dist-info/top_level.txt
metatrader_sockets_client-0.0.4.dist-info/RECORD
